globus_compute_endpoint/__init__.py
globus_compute_endpoint/auth.py
globus_compute_endpoint/boot_persistence.py
globus_compute_endpoint/cli.py
globus_compute_endpoint/exception_handling.py
globus_compute_endpoint/exceptions.py
globus_compute_endpoint/logging_config.py
globus_compute_endpoint/version.py
globus_compute_endpoint/endpoint/__init__.py
globus_compute_endpoint/endpoint/endpoint.py
globus_compute_endpoint/endpoint/endpoint_manager.py
globus_compute_endpoint/endpoint/identity_mapper.py
globus_compute_endpoint/endpoint/interchange.py
globus_compute_endpoint/endpoint/result_store.py
globus_compute_endpoint/endpoint/taskqueue.py
globus_compute_endpoint/endpoint/config/__init__.py
globus_compute_endpoint/endpoint/config/config.py
globus_compute_endpoint/endpoint/config/default_config.yaml
globus_compute_endpoint/endpoint/config/example_identity_mapping_config.json
globus_compute_endpoint/endpoint/config/model.py
globus_compute_endpoint/endpoint/config/pam.py
globus_compute_endpoint/endpoint/config/user_config_schema.json
globus_compute_endpoint/endpoint/config/user_config_template.yaml.j2
globus_compute_endpoint/endpoint/config/user_environment.yaml
globus_compute_endpoint/endpoint/config/utils.py
globus_compute_endpoint/endpoint/rabbit_mq/__init__.py
globus_compute_endpoint/endpoint/rabbit_mq/base.py
globus_compute_endpoint/endpoint/rabbit_mq/command_queue_subscriber.py
globus_compute_endpoint/endpoint/rabbit_mq/result_publisher.py
globus_compute_endpoint/endpoint/rabbit_mq/task_queue_subscriber.py
globus_compute_endpoint/endpoint/utils/__init__.py
globus_compute_endpoint/endpoint/utils/config.py
globus_compute_endpoint/engines/__init__.py
globus_compute_endpoint/engines/base.py
globus_compute_endpoint/engines/globus_compute.py
globus_compute_endpoint/engines/globus_mpi.py
globus_compute_endpoint/engines/helper.py
globus_compute_endpoint/engines/process_pool.py
globus_compute_endpoint/engines/thread_pool.py
globus_compute_endpoint/pam/__init__.py
globus_compute_endpoint-4.1.0.dist-info/licenses/LICENSE
globus_compute_endpoint-4.1.0.dist-info/METADATA
globus_compute_endpoint-4.1.0.dist-info/WHEEL
globus_compute_endpoint-4.1.0.dist-info/entry_points.txt
globus_compute_endpoint-4.1.0.dist-info/top_level.txt
globus_compute_endpoint-4.1.0.dist-info/RECORD
