Metadata-Version: 2.4
Name: globus-compute-endpoint
Version: 4.1.0
Summary: Globus Compute: High Performance Function Serving for Science
Home-page: https://github.com/globus/globus-compute
Author: Globus Compute Team
Author-email: support@globus.org
License: Apache License, Version 2.0
Project-URL: Changelog, https://globus-compute.readthedocs.io/en/latest/changelog.html
Project-URL: Upgrade to Globus Compute, https://globus-compute.readthedocs.io/en/latest/funcx_upgrade.html
Keywords: Globus Compute,FaaS,Function Serving
Classifier: Development Status :: 3 - Alpha
Classifier: Intended Audience :: Science/Research
Classifier: License :: OSI Approved :: Apache Software License
Classifier: Natural Language :: English
Classifier: Operating System :: OS Independent
Classifier: Programming Language :: Python :: 3
Classifier: Topic :: Scientific/Engineering
Requires-Python: >=3.9
License-File: LICENSE
Requires-Dist: requests<3,>=2.31.0
Requires-Dist: globus-sdk
Requires-Dist: globus-compute-sdk==4.1.0
Requires-Dist: globus-identity-mapping==0.4.0
Requires-Dist: texttable<2,>=1.6.4
Requires-Dist: psutil<6
Requires-Dist: python-daemon<3,>=2
Requires-Dist: click<8.2.0,>=8
Requires-Dist: click-option-group<1,>=0.5.6
Requires-Dist: pyzmq!=22.3.0,<=26.1.0,>=22.0.0
Requires-Dist: parsl==2025.9.15
Requires-Dist: pika>=1.2.0
Requires-Dist: pyprctl<0.2.0
Requires-Dist: setproctitle<1.4,>=1.3.2
Requires-Dist: pyyaml<7.0,>=6.0
Requires-Dist: jinja2<3.2,>=3.1.6
Requires-Dist: jsonschema<5,>=4.21
Requires-Dist: cachetools>=5.3.1
Requires-Dist: types-cachetools>=5.3.0.6
Provides-Extra: test
Requires-Dist: responses; extra == "test"
Requires-Dist: pytest>=7.2; extra == "test"
Requires-Dist: coverage>=5.2; extra == "test"
Requires-Dist: pytest-mock==3.2.0; extra == "test"
Requires-Dist: pyfakefs<5.9.2; extra == "test"
Dynamic: author
Dynamic: author-email
Dynamic: classifier
Dynamic: description
Dynamic: description-content-type
Dynamic: home-page
Dynamic: keywords
Dynamic: license
Dynamic: license-file
Dynamic: project-url
Dynamic: provides-extra
Dynamic: requires-dist
Dynamic: requires-python
Dynamic: summary
